Metadata-Version: 2.1
Name: pdfkivygui
Version: 0.1.0
Summary: Package that enables the user to use Pandas Dataframe inside Kivy Apps.
Home-page: https://github.com/jefpadfi/PandasDataframeGUIKivy
Author: Jeffrey Padfield
Author-email: 
License: UNKNOWN
Keywords: Kivy,Pandas DataFrame,Graphs
Platform: UNKNOWN
Classifier: Development Status :: 3 - Alpha
Classifier: Programming Language :: Python :: 3
Classifier: License :: OSI Approved :: MIT License
Classifier: Operating System :: OS Independent
Requires-Python: >=3.7
